cpp_project_framework/__init__.py
cpp_project_framework/create_new_project.py
cpp_project_framework-1.0.0.data/data/cpp_project_framework/.clang-format
cpp_project_framework-1.0.0.data/data/cpp_project_framework/.gitignore
cpp_project_framework-1.0.0.data/data/cpp_project_framework/CMakeSettings.json
cpp_project_framework-1.0.0.data/data/cpp_project_framework/Jenkinsfile
cpp_project_framework-1.0.0.data/data/cpp_project_framework/LICENSE
cpp_project_framework-1.0.0.data/data/cpp_project_framework/Makefile
cpp_project_framework-1.0.0.data/data/cpp_project_framework/cpp_project_framework.cmake
cpp_project_framework-1.0.0.data/data/cpp_project_framework/cpp_project_framework_callables.cmake
cpp_project_framework-1.0.0.data/data/cpp_project_framework/make.bat
cpp_project_framework-1.0.0.data/data/cpp_project_framework/template/CMakeLists.txt
cpp_project_framework-1.0.0.data/data/cpp_project_framework/template/Doxyfile
cpp_project_framework-1.0.0.data/data/cpp_project_framework/template/README.md
cpp_project_framework-1.0.0.data/data/cpp_project_framework/template/conanfile.py
cpp_project_framework-1.0.0.data/data/cpp_project_framework/template/conanfile.txt
cpp_project_framework-1.0.0.data/data/cpp_project_framework/template/template/CMakeLists.txt
cpp_project_framework-1.0.0.data/data/cpp_project_framework/template/template/Template.cpp
cpp_project_framework-1.0.0.data/data/cpp_project_framework/template/template/Template.h
cpp_project_framework-1.0.0.data/data/cpp_project_framework/template/template/Template.hpp
cpp_project_framework-1.0.0.data/data/cpp_project_framework/template/template/Template.test.cpp
cpp_project_framework-1.0.0.data/data/cpp_project_framework/template/template/main.cpp
cpp_project_framework-1.0.0.data/data/cpp_project_framework/template/tests/benchmarks/template/Template.benchmark.cpp
cpp_project_framework-1.0.0.data/data/cpp_project_framework/template/vscode/c_cpp_properties.json
cpp_project_framework-1.0.0.dist-info/LICENSE
cpp_project_framework-1.0.0.dist-info/METADATA
cpp_project_framework-1.0.0.dist-info/WHEEL
cpp_project_framework-1.0.0.dist-info/entry_points.txt
cpp_project_framework-1.0.0.dist-info/top_level.txt
cpp_project_framework-1.0.0.dist-info/RECORD
