Metadata-Version: 2.1
Name: cpp-project-framework
Version: 1.0.0
Summary: C++ Project Framework is a framework for creating C++ project.
Home-page: https://github.com/sheepgrass/cpp_project_framework
Author: Curtis Lo
License: GNU Affero General Public License v3
Classifier: Programming Language :: Python :: 3
Classifier: License :: OSI Approved :: GNU Affero General Public License v3
Classifier: Operating System :: OS Independent
Requires-Python: >=3.6
License-File: LICENSE
